CHANGES.txt
README.txt
bootstrap.py
buildout.cfg
setup.py
src/zope/__init__.py
src/zope.xmlpickle.egg-info/PKG-INFO
src/zope.xmlpickle.egg-info/SOURCES.txt
src/zope.xmlpickle.egg-info/dependency_links.txt
src/zope.xmlpickle.egg-info/namespace_packages.txt
src/zope.xmlpickle.egg-info/not-zip-safe
src/zope.xmlpickle.egg-info/requires.txt
src/zope.xmlpickle.egg-info/top_level.txt
src/zope/xmlpickle/DEPENDENCIES.cfg
src/zope/xmlpickle/__init__.py
src/zope/xmlpickle/ppml.py
src/zope/xmlpickle/xmlpickle.py
src/zope/xmlpickle/tests/__init__.py
src/zope/xmlpickle/tests/test_xmlpickle.py
