Metadata-Version: 1.0
Name: zope.xmlpickle
Version: 3.4.0
Summary: XML-based Pickling
Home-page: http://cheeseshop.python.org/pypi/zope.xmlpickle
Author: Zope Corporation and Contributors
Author-email: zope3-dev@zope.org
License: ZPL 2.1
Keywords: zope3 pickle xml
Platform: UNKNOWN
Classifier: Development Status :: 5 - Production/Stable
Classifier: Intended Audience :: Developers
Classifier: License :: OSI Approved :: Zope Public License
Classifier: Programming Language :: Python
Classifier: Natural Language :: English
Classifier: Operating System :: OS Independent
Classifier: Topic :: Internet :: WWW/HTTP
